aldryn_forms_bs4_templates/__init__.py
aldryn_forms_bs4_templates/static/aldryn_forms_bs4_templates/floating-labels.css
aldryn_forms_bs4_templates/templates/aldryn_forms/field.html
aldryn_forms_bs4_templates/templates/aldryn_forms/submit_button.html
aldryn_forms_bs4_templates/templates/aldryn_forms/fields/booleanfield.html
aldryn_forms_bs4_templates/templates/aldryn_forms/fields/filefield.html
aldryn_forms_bs4_templates/templates/aldryn_forms/fields/imagefield.html
aldryn_forms_bs4_templates/templates/aldryn_forms/fields/multiplecheckboxselectfield.html
aldryn_forms_bs4_templates/templates/aldryn_forms/fields/multipleselectfield.html
aldryn_forms_bs4_templates/templates/aldryn_forms/fields/radioselectfield.html
aldryn_forms_bs4_templates/templates/aldryn_forms/fields/selectfield.html
djangocms_aldryn_forms_bootstrap4_templates-1.0.0.2.dist-info/LICENSE
djangocms_aldryn_forms_bootstrap4_templates-1.0.0.2.dist-info/METADATA
djangocms_aldryn_forms_bootstrap4_templates-1.0.0.2.dist-info/WHEEL
djangocms_aldryn_forms_bootstrap4_templates-1.0.0.2.dist-info/top_level.txt
djangocms_aldryn_forms_bootstrap4_templates-1.0.0.2.dist-info/RECORD
