Metadata-Version: 2.1
Name: djangocms-aldryn-forms-bootstrap4-templates
Version: 1.0.0.2
Summary: Bootstrap 4 templates.
Requires-Dist: django-cms
Requires-Dist: aldryn-forms
Requires-Dist: django-sekizai
